LICENSE
README.md
setup.py
tap_s3_csv/__init__.py
tap_s3_csv/config.py
tap_s3_csv/conversion.py
tap_s3_csv/discover.py
tap_s3_csv/s3.py
tap_s3_csv/sync.py
tap_s3_csv/utils.py
tap_s3_csv.egg-info/PKG-INFO
tap_s3_csv.egg-info/SOURCES.txt
tap_s3_csv.egg-info/dependency_links.txt
tap_s3_csv.egg-info/entry_points.txt
tap_s3_csv.egg-info/requires.txt
tap_s3_csv.egg-info/top_level.txt
tests/test_all_fields.py
tests/test_all_supported_files.py
tests/test_automatic_fields.py
tests/test_bookmarks.py
tests/test_catalog_without_properties.py
tests/test_csv_with_empty_line.py
tests/test_delimiters.py
tests/test_discovery.py
tests/test_duplicate_headers_csv.py
tests/test_empty_json_jsonl_file.py
tests/test_gz_file_contains_csv_file.py
tests/test_gz_file_contains_jsonl_file.py
tests/test_gz_file_having_empty_csv.py
tests/test_gz_file_with_csv_and_jsonl_extension.py
tests/test_maximize_csv_field_width.py
tests/test_missing_key_properties.py
tests/test_no_files_match.py
tests/test_no_name_gz_file.py
tests/test_start_date.py
tests/test_targz_with_gz.py
tests/test_types_and_data.py
tests/test_zip_contains_csv_files.py
tests/test_zip_contains_csv_with_jsonl.py
tests/test_zip_contains_jsonl_file.py
tests/test_zip_contains_jsonl_with_csv.py
tests/test_zip_contains_mix_files.py
tests/test_zip_with_csv_files.py
tests/test_zip_with_jsonl_files.py