Metadata-Version: 2.1
Name: tap-s3-csv
Version: 1.5.3
Summary: Singer.io tap for extracting CSV files from S3
Home-page: https://singer.io
Author: Stitch
Classifier: Programming Language :: Python :: 3 :: Only
License-File: LICENSE
Requires-Dist: backoff==1.10.0
Requires-Dist: boto3==1.39.8
Requires-Dist: urllib3==2.5.0
Requires-Dist: singer-encodings==0.1.2
Requires-Dist: singer-python==5.13.2
Requires-Dist: voluptuous==0.15.2
Provides-Extra: dev
Requires-Dist: ipdb; extra == "dev"
